tree_sitter_yarn_spinner/__init__.py
tree_sitter_yarn_spinner/__init__.pyi
tree_sitter_yarn_spinner/_binding.abi3.so
tree_sitter_yarn_spinner/binding.c
tree_sitter_yarn_spinner/py.typed
tree_sitter_yarn_spinner-0.0.7.dist-info/METADATA
tree_sitter_yarn_spinner-0.0.7.dist-info/WHEEL
tree_sitter_yarn_spinner-0.0.7.dist-info/top_level.txt
tree_sitter_yarn_spinner-0.0.7.dist-info/RECORD
