Metadata-Version: 2.4
Name: tree-sitter-yarn-spinner
Version: 0.0.7
Summary: Tree-sitter grammar for Yarn Spinner
Author-email: yuna0x0 <yuna@yuna0x0.com>
License: MIT
Project-URL: Homepage, https://github.com/yuna0x0/tree-sitter-yarn-spinner
Keywords: incremental,parsing,tree-sitter,yarn-spinner
Classifier: Intended Audience :: Developers
Classifier: Topic :: Software Development :: Compilers
Classifier: Topic :: Text Processing :: Linguistic
Classifier: Typing :: Typed
Requires-Python: >=3.10
Provides-Extra: core
Requires-Dist: tree-sitter~=0.24; extra == "core"
